extensions/__init__.py
extensions/analysis/__init__.py
extensions/analysis/boolean_input.py
extensions/analysis/inputs.py
extensions/analysis/json_print.py
extensions/analysis/nodes.py
extensions/analysis/tf_od_api.py
extensions/analysis/tf_retinanet.py
extensions/analysis/tf_yolo.py
extensions/back/ActivationsNormalizer.py
extensions/back/AvgPool.py
extensions/back/ConvolutionNormalizer.py
extensions/back/CropToStridedSlice.py
extensions/back/CutMemory.py
extensions/back/DumpFakeQuantStat.py
extensions/back/ElementwiseOpsToEltwiseOps.py
extensions/back/EnableConstantStridedSlice.py
extensions/back/ForceStrictPrecision.py
extensions/back/FuseTransposesSequence.py
extensions/back/GatherNormalizer.py
extensions/back/GroupedConvWeightsNormalize.py
extensions/back/I64ToI32.py
extensions/back/InterpolateToInterpOrResample.py
extensions/back/LRNToNorm.py
extensions/back/LSTMCellNormalizer.py
extensions/back/LeakyReLUMutation.py
extensions/back/LeakyReluToReluWithNegativeSlope.py
extensions/back/MatMulNormalizer.py
extensions/back/MaxPool.py
extensions/back/NonMaximumSuppressionNormalize.py
extensions/back/NormalizeToNormalizeL2.py
extensions/back/OneHotNormalizer.py
extensions/back/OptimizeTransposeReshapeSequence.py
extensions/back/PackBinaryWeights.py
extensions/back/PadToV7.py
extensions/back/ParameterToPlaceholder.py
extensions/back/ProposalMutation.py
extensions/back/RNNSequenceTypeRename.py
extensions/back/ReduceToPooling.py
extensions/back/ReduceTransposeDimensions.py
extensions/back/RemoveUselessConvert.py
extensions/back/Reshape0DToSqueeze.py
extensions/back/ReshapeMutation.py
extensions/back/ResultNormalizer.py
extensions/back/ReverseInputChannels.py
extensions/back/ScalarConstNormalize.py
extensions/back/SelectBroadcast.py
extensions/back/ShapeOfToShape.py
extensions/back/ShuffleChannelPatternOptimization.py
extensions/back/ShufflenetReLUReorder.py
extensions/back/SpecialNodesFinalization.py
extensions/back/StridedSliceMasksNormalizer.py
model_optimizer-2020.2.12.dist-info/METADATA
model_optimizer-2020.2.12.dist-info/WHEEL
model_optimizer-2020.2.12.dist-info/entry_points.txt
model_optimizer-2020.2.12.dist-info/top_level.txt
model_optimizer-2020.2.12.dist-info/RECORD
